CHANGELOG.md
tocase/__init__.py
tocase/for_pandas.py
tocase/for_strings.py
tocase-1.0.0.dist-info/WHEEL
tocase-1.0.0.dist-info/METADATA
tocase-1.0.0.dist-info/RECORD
