Metadata-Version: 2.1
Name: tocase
Version: 1.0.0
Summary: tocase provides an API to recase string into any case
Home-page: https://github.com/fbraza/toCase
License: MIT
Keywords: string,pandas,regex
Author: fbraza
Author-email: fbraza@tutanota.com
Requires-Python: >=3.7.9,<4.0.0
Classifier: License :: OSI Approved :: MIT License
Classifier: Programming Language :: Python :: 3
Classifier: Programming Language :: Python :: 3.8
Classifier: Programming Language :: Python :: 3.9
Requires-Dist: regex
Project-URL: Repository, https://github.com/fbraza/toCase
